tithiwa/__init__.py
tithiwa/__main__.py
tithiwa/chatroom.py
tithiwa/constants.py
tithiwa/contact.py
tithiwa/flextithiwa.py
tithiwa/group.py
tithiwa/gui.py
tithiwa/main.py
tithiwa/session.py
tithiwa/settings.py
tithiwa/simple_gui.py
tithiwa/temp.py
tithiwa/waobject.py
tithiwa-0.1.30.dist-info/LICENSE
tithiwa-0.1.30.dist-info/METADATA
tithiwa-0.1.30.dist-info/WHEEL
tithiwa-0.1.30.dist-info/entry_points.txt
tithiwa-0.1.30.dist-info/top_level.txt
tithiwa-0.1.30.dist-info/RECORD
