Metadata-Version: 2.1
Name: tithiwa
Version: 0.1.30
Summary: tithiwa - Web WhatsApp bot: Automate Web WhatsApp with selenium in python.
Home-page: https://github.com/Tithibots/tithiwa
Author: Navpreet Devpuri and Sulagna Mukherjee
Author-email: NavpreetDevpuri@gmail.com
License: MIT License
Platform: UNKNOWN
Classifier: Programming Language :: Python :: 3.8
Classifier: Operating System :: OS Independent
Requires-Dist: selenium
Provides-Extra: dev
